odoo10_addon_business_product_location-10.0.1.0.1-py3.8-nspkg.pth
odoo/addons/business_product_location/README.rst
odoo/addons/business_product_location/__init__.py
odoo/addons/business_product_location/__manifest__.py
odoo/addons/business_product_location/i18n/am.po
odoo/addons/business_product_location/i18n/ar.po
odoo/addons/business_product_location/i18n/bg.po
odoo/addons/business_product_location/i18n/bs.po
odoo/addons/business_product_location/i18n/business_product_location.pot
odoo/addons/business_product_location/i18n/ca.po
odoo/addons/business_product_location/i18n/ca_ES.po
odoo/addons/business_product_location/i18n/cs.po
odoo/addons/business_product_location/i18n/da.po
odoo/addons/business_product_location/i18n/de.po
odoo/addons/business_product_location/i18n/el_GR.po
odoo/addons/business_product_location/i18n/en_GB.po
odoo/addons/business_product_location/i18n/es.po
odoo/addons/business_product_location/i18n/es_AR.po
odoo/addons/business_product_location/i18n/es_CL.po
odoo/addons/business_product_location/i18n/es_CO.po
odoo/addons/business_product_location/i18n/es_CR.po
odoo/addons/business_product_location/i18n/es_DO.po
odoo/addons/business_product_location/i18n/es_EC.po
odoo/addons/business_product_location/i18n/es_ES.po
odoo/addons/business_product_location/i18n/es_MX.po
odoo/addons/business_product_location/i18n/es_PE.po
odoo/addons/business_product_location/i18n/es_PY.po
odoo/addons/business_product_location/i18n/es_VE.po
odoo/addons/business_product_location/i18n/et.po
odoo/addons/business_product_location/i18n/fa.po
odoo/addons/business_product_location/i18n/fi.po
odoo/addons/business_product_location/i18n/fr.po
odoo/addons/business_product_location/i18n/fr_CA.po
odoo/addons/business_product_location/i18n/fr_CH.po
odoo/addons/business_product_location/i18n/fr_FR.po
odoo/addons/business_product_location/i18n/gl.po
odoo/addons/business_product_location/i18n/gl_ES.po
odoo/addons/business_product_location/i18n/he.po
odoo10_addon_business_product_location-10.0.1.0.1.dist-info/METADATA
odoo10_addon_business_product_location-10.0.1.0.1.dist-info/WHEEL
odoo10_addon_business_product_location-10.0.1.0.1.dist-info/namespace_packages.txt
odoo10_addon_business_product_location-10.0.1.0.1.dist-info/top_level.txt
odoo10_addon_business_product_location-10.0.1.0.1.dist-info/RECORD
